mtns_skein_hash.cp36-win32.pyd
mtns_skein_hash-1.0.dist-info/LICENSE
mtns_skein_hash-1.0.dist-info/METADATA
mtns_skein_hash-1.0.dist-info/WHEEL
mtns_skein_hash-1.0.dist-info/top_level.txt
mtns_skein_hash-1.0.dist-info/RECORD
