Metadata-Version: 1.2
Name: mtns-skein-hash
Version: 1.0
Summary: Binding for OmotenashiCoin skein algo.
Home-page: https://github.com/omotenashicoin-project/mtns-skein-python.git
Author: mtns dev
Author-email: git@omotenashicoin.site
Maintainer: mtns dev
Maintainer-email: git@omotenashicoin.site
License: MIT
Download-URL: https://github.com/omotenashicoin-project/mtns-skein-python/archive/v1.0.tar.gz
Platform: UNKNOWN
